{"name":"AdvantageDemo Platform Sign in","id":"user-sign-in;advantagedemo-platform-sign-in","testSteps":[{"number":1,"description":"Given that user get to AdvantageDemo shopping page","duration":7526,"startTime":"2024-02-01T12:24:53.615253300-05:00[America/Bogota]","screenshots":[{"screenshot":"bd1a656adcddaaaefe198912330b11c8732b934297eec53e924247d3ae0f1ac0.png","timeStamp":1706808301140},{"screenshot":"bd1a656adcddaaaefe198912330b11c8732b934297eec53e924247d3ae0f1ac0.png","timeStamp":1706808301141}],"result":"SUCCESS","precondition":false,"level":0,"children":[{"number":2,"description":"admin opens the Advantage demo home page","duration":7498,"startTime":"2024-02-01T12:24:53.631254100-05:00[America/Bogota]","screenshots":[{"screenshot":"bd1a656adcddaaaefe198912330b11c8732b934297eec53e924247d3ae0f1ac0.png","timeStamp":1706808301129}],"result":"SUCCESS","precondition":false,"level":1}]},{"number":3,"description":"And access to Sign In form","duration":2413,"startTime":"2024-02-01T12:25:01.142274200-05:00[America/Bogota]","screenshots":[{"screenshot":"42688bee26e3b79ab424982af394aac66af53246c9669dfb2bb0644a9bfefce1.png","htmlSource":"pagesource7840360708737261608.html.txt","timeStamp":1706808303510},{"screenshot":"42688bee26e3b79ab424982af394aac66af53246c9669dfb2bb0644a9bfefce1.png","htmlSource":"pagesource18290370022126729768.html.txt","timeStamp":1706808303552}],"exception":{"errorType":"org.openqa.selenium.StaleElementReferenceException","message":"stale element reference: stale element not found\n  (Session info: chrome\u003d121.0.6167.86)\nFor documentation on this error, please visit: https://www.seleniumhq.org/exceptions/stale_element_reference.html\nBuild info: version: \u00273.141.59\u0027, revision: \u0027e82be7d358\u0027, time: \u00272018-11-14T08:17:03\u0027\nSystem info: host: \u0027DESKTOP-18PT2VK\u0027, ip: \u0027192.168.1.8\u0027, os.name: \u0027Windows 10\u0027, os.arch: \u0027amd64\u0027, os.version: \u002710.0\u0027, java.version: \u002711.0.11\u0027\nDriver info: org.openqa.selenium.chrome.ChromeDriver\nCapabilities {acceptInsecureCerts: false, browserName: chrome, browserVersion: 121.0.6167.86, chrome: {chromedriverVersion: 120.0.6099.109 (3419140ab66..., userDataDir: C:\\Users\\haunt\\AppData\\Loca...}, fedcm:accounts: true, goog:chromeOptions: {debuggerAddress: localhost:53162}, javascriptEnabled: true, networkConnectionEnabled: false, pageLoadStrategy: normal, platform: WINDOWS, platformName: WINDOWS, proxy: Proxy(), setWindowRect: true, strictFileInteractability: false, timeouts: {implicit: 0, pageLoad: 300000, script: 30000}, unhandledPromptBehavior: dismiss and notify, webauthn:extension:credBlob: true, webauthn:extension:largeBlob: true, webauthn:extension:minPinLength: true, webauthn:extension:prf: true, webauthn:virtualAuthenticators: true}\nSession ID: 5d39e29e22a850c9c271e6adb0ea6fde\nFor documentation on this error, please visit: https://www.seleniumhq.org/exceptions/stale_element_reference.html\nBuild info: version: \u00273.141.59\u0027, revision: \u0027e82be7d358\u0027, time: \u00272018-11-14T08:17:03\u0027\nSystem info: host: \u0027DESKTOP-18PT2VK\u0027, ip: \u0027192.168.1.8\u0027, os.name: \u0027Windows 10\u0027, os.arch: \u0027amd64\u0027, os.version: \u002710.0\u0027, java.version: \u002711.0.11\u0027\nDriver info: driver.version: unknown","stackTrace":[{"classLoaderName":"app","declaringClass":"com.advantageonlineshop.advantagedemosuite.utils.Highlighter","methodName":"highlightElement","fileName":"Highlighter.java","lineNumber":12,"format":1},{"classLoaderName":"app","declaringClass":"com.advantageonlineshop.advantagedemosuite.stepdefinitions.SignIn","methodName":"accessToSignInForm","fileName":"SignIn.java","lineNumber":61,"format":1},{"declaringClass":"✽","methodName":"access to Sign In form","fileName":"src/test/resources/features/signin.feature","lineNumber":10,"format":0}]},"result":"ERROR","precondition":false,"level":0},{"number":4,"description":"When I fill all the required fields","duration":21,"startTime":"2024-02-01T12:25:03.557336800-05:00[America/Bogota]","result":"SKIPPED","precondition":false,"level":0},{"number":5,"description":"Then I should be successfully logged on","duration":19,"startTime":"2024-02-01T12:25:03.579337700-05:00[America/Bogota]","result":"SKIPPED","precondition":false,"level":0}],"userStory":{"id":"user-sign-in","storyName":"User Sign In","path":"src/test/resources/features/signin.feature","narrative":"  As a Web User\n  I want to register on Advantage demo\n  to buy something","type":"feature"},"featureTag":{"name":"Features/User Sign In","type":"feature","displayName":"Features/User Sign In"},"title":"AdvantageDemo Platform Sign in","tags":[{"name":"User Sign In","type":"feature","displayName":"User Sign In"}],"startTime":"2024-02-01T12:24:51.845383600-05:00[America/Bogota]","duration":11754,"testFailureCause":{"errorType":"org.openqa.selenium.StaleElementReferenceException","message":"stale element reference: stale element not found\n  (Session info: chrome\u003d121.0.6167.86)\nFor documentation on this error, please visit: https://www.seleniumhq.org/exceptions/stale_element_reference.html\nBuild info: version: \u00273.141.59\u0027, revision: \u0027e82be7d358\u0027, time: \u00272018-11-14T08:17:03\u0027\nSystem info: host: \u0027DESKTOP-18PT2VK\u0027, ip: \u0027192.168.1.8\u0027, os.name: \u0027Windows 10\u0027, os.arch: \u0027amd64\u0027, os.version: \u002710.0\u0027, java.version: \u002711.0.11\u0027\nDriver info: org.openqa.selenium.chrome.ChromeDriver\nCapabilities {acceptInsecureCerts: false, browserName: chrome, browserVersion: 121.0.6167.86, chrome: {chromedriverVersion: 120.0.6099.109 (3419140ab66..., userDataDir: C:\\Users\\haunt\\AppData\\Loca...}, fedcm:accounts: true, goog:chromeOptions: {debuggerAddress: localhost:53162}, javascriptEnabled: true, networkConnectionEnabled: false, pageLoadStrategy: normal, platform: WINDOWS, platformName: WINDOWS, proxy: Proxy(), setWindowRect: true, strictFileInteractability: false, timeouts: {implicit: 0, pageLoad: 300000, script: 30000}, unhandledPromptBehavior: dismiss and notify, webauthn:extension:credBlob: true, webauthn:extension:largeBlob: true, webauthn:extension:minPinLength: true, webauthn:extension:prf: true, webauthn:virtualAuthenticators: true}\nSession ID: 5d39e29e22a850c9c271e6adb0ea6fde\nFor documentation on this error, please visit: https://www.seleniumhq.org/exceptions/stale_element_reference.html\nBuild info: version: \u00273.141.59\u0027, revision: \u0027e82be7d358\u0027, time: \u00272018-11-14T08:17:03\u0027\nSystem info: host: \u0027DESKTOP-18PT2VK\u0027, ip: \u0027192.168.1.8\u0027, os.name: \u0027Windows 10\u0027, os.arch: \u0027amd64\u0027, os.version: \u002710.0\u0027, java.version: \u002711.0.11\u0027\nDriver info: driver.version: unknown","stackTrace":[{"classLoaderName":"app","declaringClass":"com.advantageonlineshop.advantagedemosuite.utils.Highlighter","methodName":"highlightElement","fileName":"Highlighter.java","lineNumber":12,"format":1},{"classLoaderName":"app","declaringClass":"com.advantageonlineshop.advantagedemosuite.stepdefinitions.SignIn","methodName":"accessToSignInForm","fileName":"SignIn.java","lineNumber":61,"format":1},{"declaringClass":"✽","methodName":"access to Sign In form","fileName":"src/test/resources/features/signin.feature","lineNumber":10,"format":0}]},"testFailureClassname":"org.openqa.selenium.StaleElementReferenceException","testFailureMessage":"stale element reference: stale element not found\n  (Session info: chrome\u003d121.0.6167.86)\nFor documentation on this error, please visit: https://www.seleniumhq.org/exceptions/stale_element_reference.html\nBuild info: version: \u00273.141.59\u0027, revision: \u0027e82be7d358\u0027, time: \u00272018-11-14T08:17:03\u0027\nSystem info: host: \u0027DESKTOP-18PT2VK\u0027, ip: \u0027192.168.1.8\u0027, os.name: \u0027Windows 10\u0027, os.arch: \u0027amd64\u0027, os.version: \u002710.0\u0027, java.version: \u002711.0.11\u0027\nDriver info: org.openqa.selenium.chrome.ChromeDriver\nCapabilities {acceptInsecureCerts: false, browserName: chrome, browserVersion: 121.0.6167.86, chrome: {chromedriverVersion: 120.0.6099.109 (3419140ab66..., userDataDir: C:\\Users\\haunt\\AppData\\Loca...}, fedcm:accounts: true, goog:chromeOptions: {debuggerAddress: localhost:53162}, javascriptEnabled: true, networkConnectionEnabled: false, pageLoadStrategy: normal, platform: WINDOWS, platformName: WINDOWS, proxy: Proxy(), setWindowRect: true, strictFileInteractability: false, timeouts: {implicit: 0, pageLoad: 300000, script: 30000}, unhandledPromptBehavior: dismiss and notify, webauthn:extension:credBlob: true, webauthn:extension:largeBlob: true, webauthn:extension:minPinLength: true, webauthn:extension:prf: true, webauthn:virtualAuthenticators: true}\nSession ID: 5d39e29e22a850c9c271e6adb0ea6fde\nFor documentation on this error, please visit: https://www.seleniumhq.org/exceptions/stale_element_reference.html\nBuild info: version: \u00273.141.59\u0027, revision: \u0027e82be7d358\u0027, time: \u00272018-11-14T08:17:03\u0027\nSystem info: host: \u0027DESKTOP-18PT2VK\u0027, ip: \u0027192.168.1.8\u0027, os.name: \u0027Windows 10\u0027, os.arch: \u0027amd64\u0027, os.version: \u002710.0\u0027, java.version: \u002711.0.11\u0027\nDriver info: driver.version: unknown","testFailureSummary":"ERROR;org.openqa.selenium.StaleElementReferenceException;stale element reference: stale element not found\n  (Session info: chrome\u003d121.0.6167.86)\nFor documentation on this error, please visit: https://www.seleniumhq.org/exceptions/stale_element_reference.html\nBuild info: version: \u00273.141.59\u0027, revision: \u0027e82be7d358\u0027, time: \u00272018-11-14T08:17:03\u0027\nSystem info: host: \u0027DESKTOP-18PT2VK\u0027, ip: \u0027192.168.1.8\u0027, os.name: \u0027Windows 10\u0027, os.arch: \u0027amd64\u0027, os.version: \u002710.0\u0027, java.version: \u002711.0.11\u0027\nDriver info: org.openqa.selenium.chrome.ChromeDriver\nCapabilities {acceptInsecureCerts: false, browserName: chrome, browserVersion: 121.0.6167.86, chrome: {chromedriverVersion: 120.0.6099.109 (3419140ab66..., userDataDir: C:\\Users\\haunt\\AppData\\Loca...}, fedcm:accounts: true, goog:chromeOptions: {debuggerAddress: localhost:53162}, javascriptEnabled: true, networkConnectionEnabled: false, pageLoadStrategy: normal, platform: WINDOWS, platformName: WINDOWS, proxy: Proxy(), setWindowRect: true, strictFileInteractability: false, timeouts: {implicit: 0, pageLoad: 300000, script: 30000}, unhandledPromptBehavior: dismiss and notify, webauthn:extension:credBlob: true, webauthn:extension:largeBlob: true, webauthn:extension:minPinLength: true, webauthn:extension:prf: true, webauthn:virtualAuthenticators: true}\nSession ID: 5d39e29e22a850c9c271e6adb0ea6fde\nFor documentation on this error, please visit: https://www.seleniumhq.org/exceptions/stale_element_reference.html\nBuild info: version: \u00273.141.59\u0027, revision: \u0027e82be7d358\u0027, time: \u00272018-11-14T08:17:03\u0027\nSystem info: host: \u0027DESKTOP-18PT2VK\u0027, ip: \u0027192.168.1.8\u0027, os.name: \u0027Windows 10\u0027, os.arch: \u0027amd64\u0027, os.version: \u002710.0\u0027, java.version: \u002711.0.11\u0027\nDriver info: driver.version: unknown;Highlighter.java","projectKey":"","annotatedResult":"ERROR","sessionId":"fd9d32b0c30e637780e269300feea751","driver":"chrome","isManualTestingUpToDate":false,"manual":false,"testSource":"Cucumber","actors":[{"name":"User","can":["browse the web"]},{"name":"admin","can":["browse the web"]}],"result":"ERROR"}